sipri/__init__.py
sipri/api.py
sipri-1.0.dist-info/LICENSE
sipri-1.0.dist-info/METADATA
sipri-1.0.dist-info/WHEEL
sipri-1.0.dist-info/top_level.txt
sipri-1.0.dist-info/RECORD
