Metadata-Version: 2.1
Name: sipri
Version: 1.0
Summary: A simple way to access Stockholm International Peace Research Institute's (SIPRI) trade register API and return a CSV file.
Home-page: https://github.com/smitty10010/sipri
Author: Robert S.
Author-email: 
License: MIT License
Platform: UNKNOWN
Requires-Dist: requests
